_geneant.cpython-34m.so
geneant.py
geneant-0.1.0.dist-info/METADATA
geneant-0.1.0.dist-info/RECORD
geneant-0.1.0.dist-info/WHEEL
geneant-0.1.0.dist-info/top_level.txt
.libs_geneant/libgomp-f7e03b3e.so.1.0.0
